{
    "last_updated": "12:05",
    "items": [
        {
            "title": "Tendance : horoscope 11 juillet 2026",
            "category": "Google Trends Live",
            "price": "200+ recherches",
            "viral_score": 99,
            "market_context": "Sujet chaud actuellement dans le Top 5 Google France. Volume d'intérêt maximal détecté en temps réel.",
            "image_url": "https://encrypted-tbn1.gstatic.com/images?q=tbn:ANd9GcT8w8GO2yn5rFCoOLoQJgjn9Uwr1ux6Qio7_6-WsdYP8_ST_ErVktcg3BYBmh8",
            "sourcing_url": "https://trends.google.com/trends/explore?q=horoscope%2011%20juillet%202026&geo=FR"
        },
        {
            "title": "Tendance : etape 9 tour de france 2026",
            "category": "Google Trends Live",
            "price": "100+ recherches",
            "viral_score": 98,
            "market_context": "Sujet chaud actuellement dans le Top 5 Google France. Volume d'intérêt maximal détecté en temps réel.",
            "image_url": "https://encrypted-tbn3.gstatic.com/images?q=tbn:ANd9GcTQNpx-x-UFNkdOLfLG0heIqR5CY6FAGm9I4Y2En7WY8DNMAawLb3jU4epjJJ0",
            "sourcing_url": "https://trends.google.com/trends/explore?q=etape%209%20tour%20de%20france%202026&geo=FR"
        },
        {
            "title": "Tendance : meteo montpellier",
            "category": "Google Trends Live",
            "price": "500+ recherches",
            "viral_score": 97,
            "market_context": "Sujet chaud actuellement dans le Top 5 Google France. Volume d'intérêt maximal détecté en temps réel.",
            "image_url": "https://encrypted-tbn0.gstatic.com/images?q=tbn:ANd9GcRzSqIhxVD-A3C29MRSUgiPV1xQo6cswHTfPqMc4IO6zAZ4evMG6gSythcNTCw",
            "sourcing_url": "https://trends.google.com/trends/explore?q=meteo%20montpellier&geo=FR"
        },
        {
            "title": "Tendance : nancy – troyes",
            "category": "Google Trends Live",
            "price": "1000+ recherches",
            "viral_score": 96,
            "market_context": "Sujet chaud actuellement dans le Top 5 Google France. Volume d'intérêt maximal détecté en temps réel.",
            "image_url": "https://encrypted-tbn2.gstatic.com/images?q=tbn:ANd9GcQBMg8G7bAopTzXPfP27mVZGLqJx6wFX9s8eob3hBtQDWFfC_k-eNHE3FgsdAg",
            "sourcing_url": "https://trends.google.com/trends/explore?q=nancy%20%E2%80%93%20troyes&geo=FR"
        },
        {
            "title": "Tendance : électricité",
            "category": "Google Trends Live",
            "price": "200+ recherches",
            "viral_score": 95,
            "market_context": "Sujet chaud actuellement dans le Top 5 Google France. Volume d'intérêt maximal détecté en temps réel.",
            "image_url": "https://encrypted-tbn2.gstatic.com/images?q=tbn:ANd9GcS_Fkz4xYmPAxUxe-u9prceEZuBFm2E1Q4qHUJh5MeskuObEzCxTE-uFv-RQlw",
            "sourcing_url": "https://trends.google.com/trends/explore?q=%C3%A9lectricit%C3%A9&geo=FR"
        }
    ]
}